
[
  {
    "id": 1,
    "title": "PLN and IA Seminar ",
    "date": "10 Dic, 2024",
    "time": "10:00 hrs",
    "location": "Auditorio de la E.P. de Ingeniería de Sistemas e Informática, Universidad Nacional de Moquegua, sede Ilo",
    "image": "../aimara/NLPIA.png",
    "link": "/nlpia"
  },
  {
    "id": 1,
    "title": "SIMBig 2024 ",
    "date": "20 - 22 Nov, 2024",
    "time": "10:00 hrs",
    "location": "Auditorio de la E.P. de Ingeniería de Sistemas e Informática, Universidad Nacional de Moquegua, sede Ilo",
    "image": "../aimara/simbig24.png",
    "link": "https://simbig.org/SIMBig2024/"
  },
  {
      "id": 1,
      "title": "Innovation and technological advances in the Andean region",
      "date": "03 Oct, 2024",
      "time": "10:00 hrs",
      "location": "Auditorio de la E.P. de Ingeniería de Sistemas e Informática, Universidad Nacional de Moquegua, sede Ilo",
      "image": "../aimara/andeanconference2.png",
      "link": "/andeanconference"
    },
    {
      "id": 2,
      "title": "Taller de Redacción de Artículos Científicos",
      "date": "15 Ago, 2024",
      "time": "16:00 hrs",
      "location": "Aula Magna de la E.P. de Ingeniería de Sistemas e Informática, Universidad Nacional de Moquegua, sede Ilo",
      "image": "../aimara/seminario.png",
      "link": "/Eventos_semi"
    }

  ]